{
  "212568611": {
    "_id": "212568611",
    "name": "Pretty Kitty",
    "description": "Dominant and aggressive to other cats. Will probably eat you in your sleep. Very cute tho.",
    "breed": "Bombay Cat",
    "img": "/static/images/b3de21376fdc2ce29a1b6f401.png"
  },
  "623605892": {
    "_id": "623605892",
    "name": "Pretty Kitty",
    "description": "Dominant and aggressive to other cats. Will probably eat you in your sleep. Very cute tho.",
    "breed": "Bombay Cat",
    "img": "/static/images/b3de21376fdc2ce29a1b6f403.png"
  },
  "788024807": {
    "_id": "788024807",
    "name": "Pretty Kitty",
    "description": "Dominant and aggressive to other cats. Will probably eat you in your sleep. Very cute tho.",
    "breed": "Bombay Cat",
    "img": "/static/images/b3de21376fdc2ce29a1b6f402.png"
  },
  "794415205": {
    "_id": "794415205",
    "name": "Pretty Kitty",
    "description": "Dominant and aggressive to other cats. Will probably eat you in your sleep. Very cute tho.",
    "breed": "Bombay Cat",
    "img": "/static/images/b3de21376fdc2ce29a1b6f400.png"
  },
  "965197280": {
    "_id": "965197280",
    "name": "Test",
    "description": "asdasd",
    "breed": "Bombay Cat",
    "img": "/static/images/b3de21376fdc2ce29a1b6f404.png"
  }
}